projectconnector/__init__.py
projectconnector/ActualStartDrivers/__init__.py
projectconnector/Application/__init__.py
projectconnector/Assignment/__init__.py
projectconnector/Assignments/__init__.py
projectconnector/Availabilities/__init__.py
projectconnector/Availability/__init__.py
projectconnector/Calendar/__init__.py
projectconnector/CalendarDrivers/__init__.py
projectconnector/Calendars/__init__.py
projectconnector/Cell/__init__.py
projectconnector/Chart/__init__.py
projectconnector/ChildDrivers/__init__.py
projectconnector/CodeMask/__init__.py
projectconnector/CodeMaskLevel/__init__.py
projectconnector/CostRateTable/__init__.py
projectconnector/CostRateTables/__init__.py
projectconnector/Day/__init__.py
projectconnector/Days/__init__.py
projectconnector/Engagement/__init__.py
projectconnector/EngagementComment/__init__.py
projectconnector/EngagementComments/__init__.py
projectconnector/Engagements/__init__.py
projectconnector/EventInfo/__init__.py
projectconnector/Exception/__init__.py
projectconnector/Exceptions/__init__.py
projectconnector/Filter/__init__.py
projectconnector/Filters/__init__.py
projectconnector/Group/__init__.py
projectconnector/Group2/__init__.py
projectconnector/GroupCriteria/__init__.py
projectconnector/GroupCriteria2/__init__.py
projectconnector/GroupCriterion/__init__.py
projectconnector/GroupCriterion2/__init__.py
projectconnector/Groups/__init__.py
projectconnector/Groups2/__init__.py
projectconnector/List/__init__.py
projectconnector/LookupTable/__init__.py
projectconnector/LookupTableEntry/__init__.py
projectconnector/Month/__init__.py
projectconnector/Months/__init__.py
projectconnector/OutlineCode/__init__.py
projectconnector/OutlineCodes/__init__.py
projectconnector/OverAllocatedAssignments/__init__.py
projectconnector/Pane/__init__.py
projectconnector/PayRate/__init__.py
projectconnector/PayRates/__init__.py
projectconnector/Period/__init__.py
projectconnector/PredecessorDrivers/__init__.py
projectconnector/Profile/__init__.py
projectconnector-0.1.2.dist-info/METADATA
projectconnector-0.1.2.dist-info/WHEEL
projectconnector-0.1.2.dist-info/RECORD
