Metadata-Version: 2.1
Name: projectconnector
Version: 0.1.2
Summary: 
Author: Massimo Rebuglio
Author-email: massimo.rebuglio@polito.it
Requires-Python: >=3.8,<4.0
Classifier: Programming Language :: Python :: 3
Classifier: Programming Language :: Python :: 3.8
Classifier: Programming Language :: Python :: 3.9
Classifier: Programming Language :: Python :: 3.10
Classifier: Programming Language :: Python :: 3.11
Classifier: Programming Language :: Python :: 3.12
Requires-Dist: pywin32 (==306)
